farwas/__init__.py
farwas/api.py
farwas/auth.py
farwas/cache.py
farwas/cli.py
farwas/display.py
farwas/lister.py
farwas-0.5.0.dist-info/METADATA
farwas-0.5.0.dist-info/WHEEL
farwas-0.5.0.dist-info/entry_points.txt
farwas-0.5.0.dist-info/top_level.txt
farwas-0.5.0.dist-info/RECORD
